package/__init__.py
package/main.py
telegram_gas_alert-1.0.1.dist-info/LICENSE
telegram_gas_alert-1.0.1.dist-info/METADATA
telegram_gas_alert-1.0.1.dist-info/WHEEL
telegram_gas_alert-1.0.1.dist-info/top_level.txt
telegram_gas_alert-1.0.1.dist-info/RECORD
