Metadata-Version: 2.1
Name: telegram-gas-alert
Version: 1.0.1
Summary: UNKNOWN
Home-page: https://github.com/ayuk977/telegram-gas-alert
Author: ayuk977
Author-email: ayuk977@gmail.com
License: GPL
Keywords: Telegram Gas Alert
Platform: UNKNOWN
Classifier: Programming Language :: Python :: 2.7
Classifier: Programming Language :: Python :: 3.7
Classifier: Natural Language :: English
